{"stats":{"minecraft:mined":{"minecraft:stone_pressure_plate":1,"minecraft:spruce_planks":8,"minecraft:oak_sapling":2,"minecraft:potted_cactus":1,"minecraft:brewing_stand":1,"minecraft:spruce_trapdoor":1,"minecraft:granite":48,"minecraft:red_sand":2,"minecraft:acacia_log":115,"minecraft:grass_block":746,"minecraft:chiseled_stone_bricks":2,"minecraft:smooth_stone":6,"minecraft:magma_block":2,"minecraft:iron_ore":414,"minecraft:pumpkin":5,"minecraft:white_banner":6,"minecraft:sandstone_slab":3,"minecraft:blue_banner":2,"minecraft:cut_sandstone":28,"minecraft:brown_mushroom":1,"minecraft:kelp_plant":22,"minecraft:orange_terracotta":31,"minecraft:yellow_banner":2,"minecraft:torch":30,"minecraft:light_gray_terracotta":4,"minecraft:blast_furnace":1,"minecraft:poppy":16,"minecraft:chest":9,"minecraft:dead_bush":3,"minecraft:cobblestone":85,"minecraft:prismarine":100,"minecraft:sugar_cane":4,"minecraft:oak_planks":13,"minecraft:smooth_sandstone_slab":2,"minecraft:wall_torch":24,"minecraft:seagrass":1,"minecraft:white_terracotta":6,"minecraft:blue_terracotta":1,"minecraft:birch_log":17,"minecraft:wheat":48,"minecraft:tnt":13,"minecraft:stone_brick_stairs":26,"minecraft:grass":453,"minecraft:oak_log":109,"minecraft:acacia_fence":24,"minecraft:sand":334,"minecraft:dirt":548,"minecraft:stonecutter":1,"minecraft:oak_leaves":103,"minecraft:dark_prismarine":3,"minecraft:diamond_ore":10,"minecraft:sea_lantern":2,"minecraft:ladder":1,"minecraft:dark_oak_fence":2,"minecraft:redstone_wire":3,"minecraft:acacia_slab":8,"minecraft:cartography_table":1,"minecraft:kelp":10,"minecraft:sandstone":205,"minecraft:hay_block":20,"minecraft:redstone_ore":41,"minecraft:oak_trapdoor":1,"minecraft:furnace":5,"minecraft:acacia_trapdoor":1,"minecraft:chiseled_sandstone":7,"minecraft:acacia_stairs":7,"minecraft:andesite":73,"minecraft:white_glazed_terracotta":5,"minecraft:bell":3,"minecraft:potatoes":39,"minecraft:lantern":1,"minecraft:stripped_acacia_log":4,"minecraft:wet_sponge":76,"minecraft:bamboo":29,"minecraft:stone":2115,"minecraft:redstone_wall_torch":1,"minecraft:oak_slab":1,"minecraft:acacia_leaves":57,"minecraft:scaffolding":22,"minecraft:glass_pane":4,"minecraft:stone_brick_slab":7,"minecraft:dandelion":4,"minecraft:polished_granite":3,"minecraft:oak_fence":3,"minecraft:smooth_sandstone":9,"minecraft:crafting_table":8,"minecraft:sponge":1,"minecraft:campfire":1,"minecraft:lapis_ore":24,"minecraft:diorite":78,"minecraft:prismarine_bricks":90,"minecraft:spruce_stairs":3,"minecraft:cactus":3,"minecraft:cobblestone_wall":2,"minecraft:acacia_fence_gate":2,"minecraft:redstone_torch":2,"minecraft:birch_leaves":48,"minecraft:white_wall_banner":1,"minecraft:coal_ore":279,"minecraft:gravel":732,"minecraft:cobweb":152,"minecraft:brown_terracotta":9,"minecraft:cracked_stone_bricks":6,"minecraft:terracotta":10,"minecraft:acacia_planks":40,"minecraft:stone_bricks":71,"minecraft:mossy_stone_bricks":7,"minecraft:gold_ore":37},"minecraft:used":{"minecraft:iron_shovel":2051,"minecraft:ladder":11,"minecraft:poppy":13,"minecraft:oak_sign":3,"minecraft:chest":19,"minecraft:iron_sword":489,"minecraft:stone":30,"minecraft:bell":3,"minecraft:carrot":4,"minecraft:acacia_sapling":9,"minecraft:lantern":14,"minecraft:birch_sapling":5,"minecraft:light_blue_bed":1,"minecraft:tropical_fish_spawn_egg":8,"minecraft:stone_brick_stairs":183,"minecraft:stone_bricks":1181,"minecraft:blue_banner":3,"minecraft:birch_trapdoor":4,"minecraft:red_carpet":3,"minecraft:bow":347,"minecraft:hay_block":39,"minecraft:scaffolding":129,"minecraft:oak_sapling":37,"minecraft:cooked_cod":8,"minecraft:furnace":9,"minecraft:acacia_fence":68,"minecraft:potato":5,"minecraft:seagrass":7,"minecraft:diorite":6,"minecraft:stripped_acacia_log":3,"minecraft:stone_pickaxe":482,"minecraft:acacia_trapdoor":5,"minecraft:oak_planks":89,"minecraft:wooden_pickaxe":59,"minecraft:sandstone":144,"minecraft:composter":4,"minecraft:sand":25,"minecraft:loom":1,"minecraft:blast_furnace":1,"minecraft:crossbow":88,"minecraft:sponge":26,"minecraft:redstone_torch":13,"minecraft:acacia_door":75,"minecraft:birch_slab":21,"minecraft:bread":15,"minecraft:white_glazed_terracotta":1,"minecraft:gravel":590,"minecraft:diamond_sword":1007,"minecraft:bone_meal":13,"minecraft:oak_fence":11,"minecraft:oak_trapdoor":5,"minecraft:stone_sword":148,"minecraft:stone_shovel":213,"minecraft:redstone":141,"minecraft:spruce_planks":1,"minecraft:cooked_salmon":8,"minecraft:dried_kelp_block":22,"minecraft:cooked_chicken":195,"minecraft:oak_door":17,"minecraft:torch":378,"minecraft:dirt":1176,"minecraft:prismarine_bricks":26,"minecraft:spruce_stairs":27,"minecraft:cobblestone_wall":141,"minecraft:iron_hoe":8,"minecraft:stone_brick_slab":122,"minecraft:wooden_axe":71,"minecraft:iron_axe":655,"minecraft:acacia_slab":146,"minecraft:smooth_sandstone":3,"minecraft:barrel":4,"minecraft:melon_seeds":4,"minecraft:bamboo":86,"minecraft:cooked_beef":14,"minecraft:acacia_planks":373,"minecraft:pumpkin":7,"minecraft:yellow_banner":6,"minecraft:cooked_mutton":9,"minecraft:acacia_boat":5,"minecraft:water_bucket":63,"minecraft:baked_potato":31,"minecraft:cartography_table":1,"minecraft:cut_sandstone":5,"minecraft:cauldron":2,"minecraft:stonecutter":1,"minecraft:tnt":13,"minecraft:crafting_table":15,"minecraft:campfire":2,"minecraft:smoker":1,"minecraft:acacia_stairs":90,"minecraft:diamond_pickaxe":1013,"minecraft:apple":2,"minecraft:iron_pickaxe":2497,"minecraft:spruce_trapdoor":1,"minecraft:acacia_fence_gate":8,"minecraft:stone_axe":15,"minecraft:cobblestone":841,"minecraft:white_banner":25,"minecraft:cooked_porkchop":26,"minecraft:bucket":26,"minecraft:glass_pane":65,"minecraft:dandelion":10,"minecraft:smooth_stone":38},"minecraft:custom":{"minecraft:interact_with_crafting_table":164,"minecraft:open_barrel":3,"minecraft:bell_ring":4,"minecraft:leave_game":27,"minecraft:time_since_death":635316,"minecraft:sprint_one_cm":4037777,"minecraft:damage_blocked_by_shield":5455,"minecraft:drop":10,"minecraft:talked_to_villager":25,"minecraft:deaths":9,"minecraft:jump":14868,"minecraft:walk_on_water_one_cm":493680,"minecraft:enchant_item":8,"minecraft:interact_with_furnace":259,"minecraft:interact_with_cartography_table":1,"minecraft:play_one_minute":1836485,"minecraft:interact_with_loom":13,"minecraft:sleep_in_bed":8,"minecraft:damage_dealt":40861,"minecraft:crouch_one_cm":6034,"minecraft:interact_with_smoker":12,"minecraft:horse_one_cm":127576,"minecraft:mob_kills":1426,"minecraft:fill_cauldron":2,"minecraft:climb_one_cm":45705,"minecraft:walk_one_cm":3952253,"minecraft:sneak_time":18805,"minecraft:walk_under_water_one_cm":1669818,"minecraft:boat_one_cm":499874,"minecraft:interact_with_blast_furnace":5,"minecraft:raid_trigger":1,"minecraft:interact_with_stonecutter":19,"minecraft:time_since_rest":635357,"minecraft:damage_taken":15246,"minecraft:swim_one_cm":1231471,"minecraft:fly_one_cm":1371893,"minecraft:open_chest":760,"minecraft:fall_one_cm":247346},"minecraft:crafted":{"minecraft:yellow_wool":7,"minecraft:smooth_stone":37,"minecraft:oak_planks":396,"minecraft:barrel":4,"minecraft:oak_sign":3,"minecraft:cooked_chicken":14,"minecraft:birch_slab":30,"minecraft:loom":1,"minecraft:stone":797,"minecraft:cooked_mutton":5,"minecraft:glass":63,"minecraft:bow":2,"minecraft:iron_boots":3,"minecraft:chest":7,"minecraft:acacia_fence":72,"minecraft:dried_kelp_block":25,"minecraft:yellow_banner":4,"minecraft:smoker":1,"minecraft:white_banner":1,"minecraft:arrow":320,"minecraft:cauldron":2,"minecraft:cooked_porkchop":75,"minecraft:crafting_table":7,"minecraft:spruce_planks":4,"minecraft:acacia_slab":150,"minecraft:iron_helmet":4,"minecraft:baked_potato":32,"minecraft:hay_block":12,"minecraft:birch_planks":72,"minecraft:campfire":2,"minecraft:iron_chestplate":3,"minecraft:paper":12,"minecraft:yellow_dye":8,"minecraft:shield":4,"minecraft:stick":424,"minecraft:iron_ingot":306,"minecraft:iron_pickaxe":11,"minecraft:stone_sword":2,"minecraft:light_blue_bed":1,"minecraft:acacia_door":48,"minecraft:gold_ingot":18,"minecraft:redstone_torch":5,"minecraft:sponge":89,"minecraft:shears":1,"minecraft:oak_door":15,"minecraft:redstone":9,"minecraft:stone_shovel":1,"minecraft:fishing_rod":1,"minecraft:tripwire_hook":4,"minecraft:iron_nugget":117,"minecraft:furnace":5,"minecraft:acacia_fence_gate":6,"minecraft:bone_meal":189,"minecraft:glass_pane":80,"minecraft:oak_trapdoor":4,"minecraft:scaffolding":192,"minecraft:lantern":16,"minecraft:iron_axe":3,"minecraft:ladder":6,"minecraft:iron_hoe":1,"minecraft:blue_banner":1,"minecraft:stone_pickaxe":4,"minecraft:cobblestone_wall":138,"minecraft:wheat":54,"minecraft:cooked_beef":54,"minecraft:red_dye":6,"minecraft:cooked_cod":7,"minecraft:crossbow":4,"minecraft:diamond_sword":1,"minecraft:dried_kelp":238,"minecraft:iron_sword":4,"minecraft:acacia_trapdoor":2,"minecraft:cooked_salmon":3,"minecraft:bucket":6,"minecraft:acacia_stairs":84,"minecraft:red_carpet":3,"minecraft:stone_axe":1,"minecraft:bread":1,"minecraft:acacia_boat":1,"minecraft:blue_dye":11,"minecraft:birch_trapdoor":4,"minecraft:iron_shovel":9,"minecraft:iron_leggings":3,"minecraft:acacia_planks":800,"minecraft:torch":340},"minecraft:killed":{"minecraft:cave_spider":22,"minecraft:witch":1,"minecraft:spider":17,"minecraft:skeleton":36,"minecraft:guardian":9,"minecraft:chicken":196,"minecraft:turtle":1,"minecraft:pig":7,"minecraft:zombie_villager":1,"minecraft:creeper":1,"minecraft:sheep":72,"minecraft:pillager":70,"minecraft:zombie":909,"minecraft:cow":3,"minecraft:zombie_pigman":3,"minecraft:vindicator":3,"minecraft:phantom":40,"minecraft:drowned":15,"minecraft:husk":4,"minecraft:rabbit":3,"minecraft:bat":2,"minecraft:enderman":2},"minecraft:picked_up":{"minecraft:seagrass":1,"minecraft:wheat":17,"minecraft:prismarine_shard":11,"minecraft:flower_pot":2,"minecraft:yellow_wool":9,"minecraft:diamond_sword":1,"minecraft:potion":1,"minecraft:stone_brick_stairs":26,"minecraft:brewing_stand":1,"minecraft:string":190,"minecraft:smooth_stone_slab":2,"minecraft:red_sand":14,"minecraft:gold_nugget":3,"minecraft:smooth_stone":6,"minecraft:spruce_planks":8,"minecraft:acacia_fence_gate":2,"minecraft:redstone_torch":11,"minecraft:furnace":5,"minecraft:blue_wool":4,"minecraft:stick":21,"minecraft:white_glazed_terracotta":9,"minecraft:acacia_fence":41,"minecraft:brown_terracotta":9,"minecraft:oak_fence":11,"minecraft:torch":142,"minecraft:acacia_log":191,"minecraft:spruce_stairs":3,"minecraft:porkchop":16,"minecraft:diorite":86,"minecraft:rabbit_foot":2,"minecraft:yellow_banner":2,"minecraft:cactus":8,"minecraft:rotten_flesh":689,"minecraft:light_blue_wool":15,"minecraft:tropical_fish":3,"minecraft:white_terracotta":6,"minecraft:cod":5,"minecraft:cobblestone":2188,"minecraft:sponge":1,"minecraft:birch_log":17,"minecraft:magma_block":2,"minecraft:cooked_beef":1,"minecraft:feather":186,"minecraft:andesite":74,"minecraft:brown_wool":5,"minecraft:potato":58,"minecraft:flint":83,"minecraft:prismarine_bricks":102,"minecraft:acacia_boat":5,"minecraft:lantern":1,"minecraft:lapis_lazuli":148,"minecraft:dirt":1365,"minecraft:polished_granite":3,"minecraft:bone":42,"minecraft:acacia_planks":113,"minecraft:stonecutter":1,"minecraft:bow":3,"minecraft:wheat_seeds":141,"minecraft:bell":3,"minecraft:rabbit":1,"minecraft:mossy_stone_bricks":7,"minecraft:bamboo":275,"minecraft:prismarine":93,"minecraft:oak_planks":17,"minecraft:oak_pressure_plate":1,"minecraft:sand":448,"minecraft:ink_sac":3,"minecraft:acacia_stairs":9,"minecraft:chiseled_sandstone":7,"minecraft:orange_wool":2,"minecraft:dark_prismarine":3,"minecraft:stripped_acacia_log":4,"minecraft:light_gray_terracotta":4,"minecraft:blue_terracotta":1,"minecraft:diamond":10,"minecraft:crossbow":8,"minecraft:granite":48,"minecraft:emerald":1,"minecraft:blue_banner":2,"minecraft:oak_sapling":17,"minecraft:dark_oak_fence":2,"minecraft:fishing_rod":1,"minecraft:charcoal":2,"minecraft:crafting_table":7,"minecraft:sandstone_slab":1,"minecraft:chicken":185,"minecraft:ladder":5,"minecraft:brown_mushroom":1,"minecraft:pink_wool":6,"minecraft:oak_trapdoor":1,"minecraft:acacia_door":28,"minecraft:cracked_stone_bricks":6,"minecraft:cartography_table":1,"minecraft:beef":6,"minecraft:oak_boat":1,"minecraft:poppy":18,"minecraft:light_gray_wool":2,"minecraft:chest":10,"minecraft:sugar_cane":6,"minecraft:birch_sapling":5,"minecraft:spruce_trapdoor":1,"minecraft:phantom_membrane":19,"minecraft:egg":127,"minecraft:sandstone":188,"minecraft:oak_door":1,"minecraft:carrot":2,"minecraft:redstone":172,"minecraft:prismarine_crystals":11,"minecraft:stone_pressure_plate":1,"minecraft:smooth_sandstone_slab":2,"minecraft:tnt":13,"minecraft:arrow":150,"minecraft:cooked_cod":7,"minecraft:hay_block":19,"minecraft:mutton":94,"minecraft:white_wool":21,"minecraft:rail":8,"minecraft:wet_sponge":89,"minecraft:cut_sandstone":26,"minecraft:leather":4,"minecraft:filled_map":2,"minecraft:oak_log":109,"minecraft:gunpowder":4,"minecraft:cobblestone_wall":2,"minecraft:white_banner":24,"minecraft:orange_terracotta":34,"minecraft:smooth_sandstone":6,"minecraft:apple":1,"minecraft:stone_bricks":71,"minecraft:kelp":42,"minecraft:acacia_trapdoor":1,"minecraft:rabbit_hide":1,"minecraft:iron_ingot":7,"minecraft:cooked_chicken":1,"minecraft:iron_ore":405,"minecraft:glass_bottle":2,"minecraft:acacia_sapling":9,"minecraft:oak_slab":1,"minecraft:scaffolding":106,"minecraft:pumpkin":5,"minecraft:chiseled_stone_bricks":2,"minecraft:stone_brick_slab":7,"minecraft:red_wool":6,"minecraft:dandelion":5,"minecraft:gravel":657,"minecraft:blast_furnace":1,"minecraft:spruce_log":1,"minecraft:gold_ore":37,"minecraft:spider_eye":11,"minecraft:polished_diorite":1,"minecraft:painting":1,"minecraft:terracotta":10,"minecraft:acacia_slab":8,"minecraft:melon_seeds":3,"minecraft:coal":302,"minecraft:ender_pearl":2},"minecraft:dropped":{"minecraft:cooked_porkchop":1,"minecraft:cut_sandstone":5,"minecraft:heart_of_the_sea":1,"minecraft:filled_map":3},"minecraft:killed_by":{"minecraft:elder_guardian":1,"minecraft:zombie_pigman":1,"minecraft:guardian":1},"minecraft:broken":{"minecraft:iron_shovel":7,"minecraft:stone_pickaxe":3,"minecraft:iron_sword":2,"minecraft:wooden_axe":1,"minecraft:bow":1,"minecraft:stone_shovel":1,"minecraft:wooden_pickaxe":1,"minecraft:shield":1,"minecraft:iron_axe":1,"minecraft:iron_pickaxe":8,"minecraft:iron_helmet":1}},"DataVersion":1952}